aws_services/__init__.py
aws_services/dynamodb_utils.py
aws_services/sns_utils.py
aws_services_library-0.0.6.dist-info/LICENSE
aws_services_library-0.0.6.dist-info/METADATA
aws_services_library-0.0.6.dist-info/WHEEL
aws_services_library-0.0.6.dist-info/top_level.txt
aws_services_library-0.0.6.dist-info/RECORD
