Metadata-Version: 2.2
Name: aws_services_library
Version: 0.0.6
Summary: AWS SNS and DynamoDB library for Django applications
Home-page: https://github.com/kornerstonecoker/aws_services_library
Author: Simon Coker
Author-email: kornerstonecoker@gmail.com
Classifier: Programming Language :: Python :: 3
Classifier: License :: OSI Approved :: MIT License
Classifier: Operating System :: OS Independent
Requires-Python: >=3.6
License-File: LICENSE
Requires-Dist: boto3
Dynamic: author
Dynamic: author-email
Dynamic: classifier
Dynamic: description-content-type
Dynamic: home-page
Dynamic: requires-dist
Dynamic: requires-python
Dynamic: summary
